{
  "schemaVersion": 1,
  "id": "meow-library",
  "version": "${version}",
  "name": "Meow Server S4",
  "description": "A Meow Server Extra Experience Mod.",
  "authors": [
    "Meow Research"
  ],
  "contact": {
    "homepage": "https://mc.meowshe.com/",
    "sources": "https://github.com/MeowShe/meowserver"
  },
  "license": "CC0-1.0",
  "icon": "assets/meow-server-s4/icon.png",
  "environment": "*",
  "entrypoints": {
    "main": [
      "io.meowresearch.mcserver.s4.MeowServerS4"
    ]
  },
  "mixins": [
    "meow-server-s4.mixins.json",
    {
      "config": "meow-server-s4.client.mixins.json",
      "environment": "client"
    }
  ],
  "depends": {
    "fabricloader": ">=0.15.11",
    "minecraft": "~1.21",
    "java": ">=21",
    "fabric-api": "*"
  },
  "suggests": {
    "another-mod": "*"
  }
}